{
  "createdAt": "2018-04-15T22:28:50Z",
  "description": "Microsoft Integration, Azure, Power Platform, Office 365 and much more Stencils Pack it’s a Visio package that contains fully resizable Visio shapes (symbols/icons) that will help you to visually represent On-premise, Cloud or Hybrid Integration and Enterprise architectures scenarios (BizTalk Server, API Management, Logic Apps, Service Bus, Event Hub…), solutions diagrams and features or systems that use Microsoft Azure and related cloud and on-premises technologies in Visio 2016/2013",
  "fullName": "sandroasp/Microsoft-Integration-and-Azure-Stencils-Pack-for-Visio",
  "repositoryId": 129656417,
  "hasIssues": true,
  "homepage": "https://blog.sandro-pereira.com/",
  "isArchived": false,
  "language": "PowerShell",
  "license": {
    "key": "mit",
    "name": "MIT License",
    "url": "https://api.github.com/licenses/mit"
  },
  "name": "Microsoft-Integration-and-Azure-Stencils-Pack-for-Visio",
  "openIssuesCount": 5,
  "owner": {
    "id": "1318263",
    "is_bot": false,
    "login": "sandroasp",
    "type": "User",
    "url": "https://github.com/sandroasp"
  },
  "updatedAt": "2026-06-19T10:32:46Z",
  "url": "https://github.com/sandroasp/Microsoft-Integration-and-Azure-Stencils-Pack-for-Visio",
  "codeOfConduct": null,
  "forkCount": 446,
  "fundingLinks": [],
  "isSecurityPolicyEnabled": false,
  "isTemplate": false,
  "latestRelease": {
    "name": "Microsoft Integration, Azure, BAPI, Office 365 and much more Stencils Pack v7.2.0",
    "tagName": "7.2.0",
    "url": "https://github.com/sandroasp/Microsoft-Integration-and-Azure-Stencils-Pack-for-Visio/releases/tag/7.2.0",
    "publishedAt": "2021-06-21T13:48:29Z"
  },
  "primaryLanguage": {
    "name": "PowerShell"
  },
  "securityPolicyUrl": null,
  "stargazerCount": 1521,
  "watchers": {
    "totalCount": 122
  },
  "topics": [
    "stencils",
    "stencils-pack",
    "mis-azure",
    "support-stencils",
    "systems-logo-stencils",
    "sap-stencils",
    "integration",
    "azure",
    "power-platform",
    "office-365",
    "visio",
    "resizable-visio-shapes",
    "shapes",
    "mis-devices-stencils",
    "office"
  ],
  "languages": [
    "PowerShell"
  ],
  "openedGoodFirstIssues": 0,
  "hasGoodFirstIssues": false,
  "openedHelpWantedIssues": 0,
  "hasHelpWantedIssues": false,
  "openedToContributionsIssues": 0,
  "popularityScore": 1643,
  "_schemaVersion": "1.0.0",
  "_generatedAt": "2026-06-24T11:57:37.954Z",
  "_workflowRunId": "28096733932"
}
