{
  "createdAt": "2022-09-28T19:47:05Z",
  "description": "D365 FSC DevOps setup&maintenance tools for GitHub",
  "fullName": "fscpscollaborative/fscps",
  "repositoryId": 542766389,
  "hasIssues": true,
  "homepage": "",
  "isArchived": false,
  "language": "PowerShell",
  "license": {
    "key": "apache-2.0",
    "name": "Apache License 2.0",
    "url": "https://api.github.com/licenses/apache-2.0"
  },
  "name": "fscps",
  "openIssuesCount": 3,
  "owner": {
    "id": "168817300",
    "is_bot": false,
    "login": "fscpscollaborative",
    "type": "Organization",
    "url": "https://github.com/fscpscollaborative"
  },
  "updatedAt": "2026-05-21T00:28:38Z",
  "url": "https://github.com/fscpscollaborative/fscps",
  "codeOfConduct": null,
  "forkCount": 6,
  "fundingLinks": [],
  "isSecurityPolicyEnabled": false,
  "isTemplate": false,
  "latestRelease": null,
  "primaryLanguage": {
    "name": "PowerShell"
  },
  "securityPolicyUrl": null,
  "stargazerCount": 29,
  "watchers": {
    "totalCount": 4
  },
  "topics": [
    "d365fo",
    "dynamics-365",
    "powershell",
    "d365tools",
    "d365",
    "devops-tools",
    "fsc",
    "retail",
    "d365actions",
    "devops",
    "365",
    "dynamics",
    "fscps",
    "fscps-tools"
  ],
  "languages": [
    "PowerShell",
    "C#"
  ],
  "openedGoodFirstIssues": 0,
  "hasGoodFirstIssues": false,
  "openedHelpWantedIssues": 0,
  "hasHelpWantedIssues": false,
  "openedToContributionsIssues": 0,
  "popularityScore": 33,
  "_schemaVersion": "1.0.0",
  "_generatedAt": "2026-05-21T12:05:51.774Z",
  "_workflowRunId": "26224837636"
}
