{
  "createdAt": "2017-01-15T02:02:48Z",
  "description": "A Dynamics CRM Add-In for speeding up tasks such as translating or toggling field security on or off",
  "fullName": "XRM-OSS/Xrm-Quick-Edit",
  "repositoryId": 78986335,
  "hasIssues": true,
  "homepage": "",
  "isArchived": false,
  "language": "JavaScript",
  "license": {
    "key": "mit",
    "name": "MIT License",
    "url": "https://api.github.com/licenses/mit"
  },
  "name": "Xrm-Quick-Edit",
  "openIssuesCount": 8,
  "owner": {
    "id": "25161848",
    "is_bot": false,
    "login": "XRM-OSS",
    "type": "Organization",
    "url": "https://github.com/XRM-OSS"
  },
  "updatedAt": "2026-04-09T06:10:03Z",
  "url": "https://github.com/XRM-OSS/Xrm-Quick-Edit",
  "codeOfConduct": null,
  "forkCount": 4,
  "fundingLinks": [],
  "isSecurityPolicyEnabled": false,
  "isTemplate": false,
  "latestRelease": {
    "name": "Release v3.17.0",
    "tagName": "v3.17.0",
    "url": "https://github.com/XRM-OSS/Xrm-Quick-Edit/releases/tag/v3.17.0",
    "publishedAt": "2023-05-26T05:26:36Z"
  },
  "primaryLanguage": {
    "name": "JavaScript"
  },
  "securityPolicyUrl": null,
  "stargazerCount": 17,
  "watchers": {
    "totalCount": 4
  },
  "topics": [
    "dynamics-crm",
    "dynamics-365",
    "translation",
    "labels",
    "dashboard",
    "solution",
    "xrm",
    "bulk",
    "update"
  ],
  "languages": [
    "JavaScript",
    "HTML"
  ],
  "openedGoodFirstIssues": 0,
  "hasGoodFirstIssues": false,
  "openedHelpWantedIssues": 0,
  "hasHelpWantedIssues": false,
  "openedToContributionsIssues": 0,
  "popularityScore": 21,
  "_schemaVersion": "1.0.0",
  "_generatedAt": "2026-06-24T11:57:37.954Z",
  "_workflowRunId": "28096733932"
}
