{
  "createdAt": "2021-02-24T22:16:04Z",
  "description": "Contains curated community Microsoft Power App samples",
  "fullName": "pnp/powerapps-samples",
  "repositoryId": 342050865,
  "hasIssues": true,
  "homepage": "https://aka.ms/powerplatform-samples",
  "isArchived": false,
  "language": "",
  "license": {
    "key": "mit",
    "name": "MIT License",
    "url": "https://api.github.com/licenses/mit"
  },
  "name": "powerapps-samples",
  "openIssuesCount": 39,
  "owner": {
    "id": "31443929",
    "is_bot": false,
    "login": "pnp",
    "type": "Organization",
    "url": "https://github.com/pnp"
  },
  "updatedAt": "2026-06-11T17:45:04Z",
  "url": "https://github.com/pnp/powerapps-samples",
  "codeOfConduct": {
    "key": "other",
    "name": "Other",
    "url": "https://github.com/pnp/powerapps-samples/blob/main/CODE_OF_CONDUCT.md"
  },
  "forkCount": 340,
  "fundingLinks": [],
  "isSecurityPolicyEnabled": true,
  "isTemplate": false,
  "latestRelease": null,
  "primaryLanguage": null,
  "securityPolicyUrl": "https://github.com/pnp/powerapps-samples/security/policy",
  "stargazerCount": 528,
  "watchers": {
    "totalCount": 37
  },
  "topics": [
    "powerapps",
    "powerplatform",
    "hacktoberfest"
  ],
  "languages": [],
  "openedGoodFirstIssues": 0,
  "hasGoodFirstIssues": false,
  "openedHelpWantedIssues": 0,
  "hasHelpWantedIssues": false,
  "openedToContributionsIssues": 0,
  "popularityScore": 565,
  "_schemaVersion": "1.0.0",
  "_generatedAt": "2026-06-23T12:03:34.481Z",
  "_workflowRunId": "28024761014"
}
