{
  "createdAt": "2016-05-20T12:32:41Z",
  "description": "Chrome, Edge Chromium and Firefox Extension for Dynamics CRM/365/Power Apps Power users",
  "fullName": "rajyraman/Levelup-for-Dynamics-CRM",
  "repositoryId": 59292748,
  "hasIssues": true,
  "homepage": "",
  "isArchived": false,
  "language": "TypeScript",
  "license": {
    "key": "mit",
    "name": "MIT License",
    "url": "https://api.github.com/licenses/mit"
  },
  "name": "Levelup-for-Dynamics-CRM",
  "openIssuesCount": 48,
  "owner": {
    "id": "5035266",
    "is_bot": false,
    "login": "rajyraman",
    "type": "User",
    "url": "https://github.com/rajyraman"
  },
  "updatedAt": "2026-06-05T10:10:26Z",
  "url": "https://github.com/rajyraman/Levelup-for-Dynamics-CRM",
  "codeOfConduct": null,
  "forkCount": 99,
  "fundingLinks": [],
  "isSecurityPolicyEnabled": false,
  "isTemplate": false,
  "latestRelease": {
    "name": "Level Up v4.1.3",
    "tagName": "v4.1.3",
    "url": "https://github.com/rajyraman/Levelup-for-Dynamics-CRM/releases/tag/v4.1.3",
    "publishedAt": "2025-09-05T02:54:30Z"
  },
  "primaryLanguage": {
    "name": "TypeScript"
  },
  "securityPolicyUrl": null,
  "stargazerCount": 262,
  "watchers": {
    "totalCount": 23
  },
  "topics": [
    "dynamics-crm",
    "chrome-extension",
    "dynamics-365",
    "powerapps",
    "dataverse",
    "power-apps"
  ],
  "languages": [
    "TypeScript",
    "CSS",
    "JavaScript",
    "HTML"
  ],
  "openedGoodFirstIssues": 0,
  "hasGoodFirstIssues": false,
  "openedHelpWantedIssues": 0,
  "hasHelpWantedIssues": false,
  "openedToContributionsIssues": 0,
  "popularityScore": 285,
  "_schemaVersion": "1.0.0",
  "_generatedAt": "2026-06-10T12:07:41.910Z",
  "_workflowRunId": "27275074952"
}
